{
  "name" : "ObjectUtils",
  "qualifiedName" : "io.fluxzero.common.ObjectUtils",
  "packageName" : "io.fluxzero.common",
  "kind" : "class",
  "modifiers" : [ "public" ],
  "annotations" : [ {
    "annotationType" : "lombok.extern.slf4j.Slf4j",
    "values" : {}
  } ],
  "documentation" : " Utility class for common object handling, memoization, concurrency, stream processing, and error handling.\n <p>\n Offers reusable tools for:\n <ul>\n   <li>Memoizing functional interfaces</li>\n   <li>Retry-safe functional wrappers (callables, consumers, etc.)</li>\n   <li>Stream deduplication and flattening</li>\n   <li>Property file manipulation</li>\n   <li>Exception-safe task execution and error unwrapping</li>\n   <li>Custom thread factories and naming</li>\n </ul>\n",
  "typeParameters" : [ ],
  "superClass" : "java.lang.Object",
  "interfaces" : [ ],
  "fields" : [ {
    "name" : "noOpBiPredicate",
    "qualifiedName" : "io.fluxzero.common.ObjectUtils.noOpBiPredicate",
    "type" : "java.util.function.BiPredicate<java.lang.Object,java.lang.Object>",
    "modifiers" : [ "final", "private", "static" ],
    "annotations" : [ ],
    "documentation" : null,
    "constantValue" : null
  }, {
    "name" : "noOpPredicate",
    "qualifiedName" : "io.fluxzero.common.ObjectUtils.noOpPredicate",
    "type" : "java.util.function.Predicate<java.lang.Object>",
    "modifiers" : [ "final", "private", "static" ],
    "annotations" : [ ],
    "documentation" : null,
    "constantValue" : null
  } ],
  "constructors" : [ {
    "name" : "ObjectUtils",
    "qualifiedName" : "io.fluxzero.common.ObjectUtils#ObjectUtils",
    "modifiers" : [ "public" ],
    "annotations" : [ ],
    "typeParameters" : [ ],
    "parameters" : [ ],
    "thrownTypes" : [ ],
    "varArgs" : false,
    "documentation" : null
  } ],
  "methods" : [ {
    "name" : "asCallable",
    "qualifiedName" : "io.fluxzero.common.ObjectUtils#asCallable",
    "returnType" : "java.util.concurrent.Callable<?>",
    "modifiers" : [ "public", "static" ],
    "annotations" : [ ],
    "typeParameters" : [ ],
    "parameters" : [ {
      "name" : "runnable",
      "type" : "io.fluxzero.common.ThrowingRunnable",
      "varArgs" : false,
      "annotations" : [ ]
    } ],
    "thrownTypes" : [ ],
    "varArgs" : false,
    "documentation" : " Converts a ThrowingRunnable into a {@code Callable<Object>} that returns null.\n"
  }, {
    "name" : "asCallable",
    "qualifiedName" : "io.fluxzero.common.ObjectUtils#asCallable",
    "returnType" : "java.util.concurrent.Callable<?>",
    "modifiers" : [ "public", "static" ],
    "annotations" : [ ],
    "typeParameters" : [ ],
    "parameters" : [ {
      "name" : "runnable",
      "type" : "java.lang.Runnable",
      "varArgs" : false,
      "annotations" : [ ]
    } ],
    "thrownTypes" : [ ],
    "varArgs" : false,
    "documentation" : " Converts a standard {@link Runnable} into a {@code Callable<Object>} that returns null.\n"
  }, {
    "name" : "asConsumer",
    "qualifiedName" : "io.fluxzero.common.ObjectUtils#asConsumer",
    "returnType" : "java.util.function.Consumer<T>",
    "modifiers" : [ "public", "static" ],
    "annotations" : [ ],
    "typeParameters" : [ "T" ],
    "parameters" : [ {
      "name" : "consumer",
      "type" : "io.fluxzero.common.ThrowingConsumer<T>",
      "varArgs" : false,
      "annotations" : [ ]
    } ],
    "thrownTypes" : [ ],
    "varArgs" : false,
    "documentation" : null
  }, {
    "name" : "asFunction",
    "qualifiedName" : "io.fluxzero.common.ObjectUtils#asFunction",
    "returnType" : "java.util.function.Function<T,R>",
    "modifiers" : [ "public", "static" ],
    "annotations" : [ ],
    "typeParameters" : [ "T", "R" ],
    "parameters" : [ {
      "name" : "function",
      "type" : "io.fluxzero.common.ThrowingFunction<T,R>",
      "varArgs" : false,
      "annotations" : [ ]
    } ],
    "thrownTypes" : [ ],
    "varArgs" : false,
    "documentation" : null
  }, {
    "name" : "asProperties",
    "qualifiedName" : "io.fluxzero.common.ObjectUtils#asProperties",
    "returnType" : "java.util.Properties",
    "modifiers" : [ "public", "static" ],
    "annotations" : [ {
      "annotationType" : "lombok.SneakyThrows",
      "values" : {}
    } ],
    "typeParameters" : [ ],
    "parameters" : [ {
      "name" : "content",
      "type" : "java.lang.String",
      "varArgs" : false,
      "annotations" : [ ]
    } ],
    "thrownTypes" : [ ],
    "varArgs" : false,
    "documentation" : " Parses Java {@link Properties} from a string.\n"
  }, {
    "name" : "asRunnable",
    "qualifiedName" : "io.fluxzero.common.ObjectUtils#asRunnable",
    "returnType" : "java.lang.Runnable",
    "modifiers" : [ "public", "static" ],
    "annotations" : [ ],
    "typeParameters" : [ ],
    "parameters" : [ {
      "name" : "runnable",
      "type" : "io.fluxzero.common.ThrowingRunnable",
      "varArgs" : false,
      "annotations" : [ ]
    } ],
    "thrownTypes" : [ ],
    "varArgs" : false,
    "documentation" : null
  }, {
    "name" : "asRunnable",
    "qualifiedName" : "io.fluxzero.common.ObjectUtils#asRunnable",
    "returnType" : "java.lang.Runnable",
    "modifiers" : [ "public", "static" ],
    "annotations" : [ ],
    "typeParameters" : [ ],
    "parameters" : [ {
      "name" : "callable",
      "type" : "java.util.concurrent.Callable<?>",
      "varArgs" : false,
      "annotations" : [ ]
    } ],
    "thrownTypes" : [ ],
    "varArgs" : false,
    "documentation" : null
  }, {
    "name" : "asStream",
    "qualifiedName" : "io.fluxzero.common.ObjectUtils#asStream",
    "returnType" : "java.util.stream.Stream<?>",
    "modifiers" : [ "public", "static" ],
    "annotations" : [ ],
    "typeParameters" : [ ],
    "parameters" : [ {
      "name" : "value",
      "type" : "java.lang.Object",
      "varArgs" : false,
      "annotations" : [ ]
    } ],
    "thrownTypes" : [ ],
    "varArgs" : false,
    "documentation" : " Converts an object into a stream. Supports Collection, Stream, Optional, or single value.\n"
  }, {
    "name" : "asSupplier",
    "qualifiedName" : "io.fluxzero.common.ObjectUtils#asSupplier",
    "returnType" : "java.util.function.Supplier<T>",
    "modifiers" : [ "public", "static" ],
    "annotations" : [ ],
    "typeParameters" : [ "T" ],
    "parameters" : [ {
      "name" : "callable",
      "type" : "java.util.concurrent.Callable<T>",
      "varArgs" : false,
      "annotations" : [ ]
    } ],
    "thrownTypes" : [ ],
    "varArgs" : false,
    "documentation" : null
  }, {
    "name" : "call",
    "qualifiedName" : "io.fluxzero.common.ObjectUtils#call",
    "returnType" : "T",
    "modifiers" : [ "public", "static" ],
    "annotations" : [ {
      "annotationType" : "lombok.SneakyThrows",
      "values" : {}
    } ],
    "typeParameters" : [ "T" ],
    "parameters" : [ {
      "name" : "callable",
      "type" : "java.util.concurrent.Callable<T>",
      "varArgs" : false,
      "annotations" : [ ]
    } ],
    "thrownTypes" : [ ],
    "varArgs" : false,
    "documentation" : " Calls the given callable, forcibly rethrowing exceptions.\n"
  }, {
    "name" : "concat",
    "qualifiedName" : "io.fluxzero.common.ObjectUtils#concat",
    "returnType" : "java.util.stream.Stream<T>",
    "modifiers" : [ "public", "static" ],
    "annotations" : [ {
      "annotationType" : "java.lang.SafeVarargs",
      "values" : {}
    } ],
    "typeParameters" : [ "T" ],
    "parameters" : [ {
      "name" : "streams",
      "type" : "java.util.stream.Stream<? extends T>[]",
      "varArgs" : true,
      "annotations" : [ ]
    } ],
    "thrownTypes" : [ ],
    "varArgs" : true,
    "documentation" : " Concatenates multiple streams into a single flat stream.\n"
  }, {
    "name" : "copyOf",
    "qualifiedName" : "io.fluxzero.common.ObjectUtils#copyOf",
    "returnType" : "java.util.Properties",
    "modifiers" : [ "public", "static" ],
    "annotations" : [ ],
    "typeParameters" : [ ],
    "parameters" : [ {
      "name" : "properties",
      "type" : "java.util.Properties",
      "varArgs" : false,
      "annotations" : [ ]
    } ],
    "thrownTypes" : [ ],
    "varArgs" : false,
    "documentation" : " Creates a deep copy of a Properties instance.\n"
  }, {
    "name" : "deduplicate",
    "qualifiedName" : "io.fluxzero.common.ObjectUtils#deduplicate",
    "returnType" : "java.util.List<T>",
    "modifiers" : [ "public", "static" ],
    "annotations" : [ ],
    "typeParameters" : [ "T" ],
    "parameters" : [ {
      "name" : "list",
      "type" : "java.util.List<T>",
      "varArgs" : false,
      "annotations" : [ ]
    } ],
    "thrownTypes" : [ ],
    "varArgs" : false,
    "documentation" : " Deduplicates elements in the list, preserving the last occurrence.\n"
  }, {
    "name" : "deduplicate",
    "qualifiedName" : "io.fluxzero.common.ObjectUtils#deduplicate",
    "returnType" : "java.util.List<T>",
    "modifiers" : [ "public", "static" ],
    "annotations" : [ ],
    "typeParameters" : [ "T" ],
    "parameters" : [ {
      "name" : "list",
      "type" : "java.util.List<T>",
      "varArgs" : false,
      "annotations" : [ ]
    }, {
      "name" : "idFunction",
      "type" : "java.util.function.Function<T,?>",
      "varArgs" : false,
      "annotations" : [ ]
    } ],
    "thrownTypes" : [ ],
    "varArgs" : false,
    "documentation" : " Deduplicates elements using a key extractor, preserving the last occurrence.\n"
  }, {
    "name" : "deduplicate",
    "qualifiedName" : "io.fluxzero.common.ObjectUtils#deduplicate",
    "returnType" : "java.util.List<T>",
    "modifiers" : [ "public", "static" ],
    "annotations" : [ ],
    "typeParameters" : [ "T" ],
    "parameters" : [ {
      "name" : "list",
      "type" : "java.util.List<T>",
      "varArgs" : false,
      "annotations" : [ ]
    }, {
      "name" : "idFunction",
      "type" : "java.util.function.Function<T,?>",
      "varArgs" : false,
      "annotations" : [ ]
    }, {
      "name" : "keepFirst",
      "type" : "boolean",
      "varArgs" : false,
      "annotations" : [ ]
    } ],
    "thrownTypes" : [ ],
    "varArgs" : false,
    "documentation" : " Deduplicates elements using a key extractor, optionally keeping the first occurrence.\n"
  }, {
    "name" : "distinctByKey",
    "qualifiedName" : "io.fluxzero.common.ObjectUtils#distinctByKey",
    "returnType" : "java.util.function.Predicate<T>",
    "modifiers" : [ "public", "static" ],
    "annotations" : [ ],
    "typeParameters" : [ "T" ],
    "parameters" : [ {
      "name" : "keyExtractor",
      "type" : "java.util.function.Function<? super T,?>",
      "varArgs" : false,
      "annotations" : [ ]
    } ],
    "thrownTypes" : [ ],
    "varArgs" : false,
    "documentation" : " Returns a predicate that filters out duplicates based on a key extractor.\n"
  }, {
    "name" : "forceThrow",
    "qualifiedName" : "io.fluxzero.common.ObjectUtils#forceThrow",
    "returnType" : "java.lang.Object",
    "modifiers" : [ "public", "static" ],
    "annotations" : [ {
      "annotationType" : "lombok.SneakyThrows",
      "values" : {}
    } ],
    "typeParameters" : [ ],
    "parameters" : [ {
      "name" : "error",
      "type" : "java.lang.Throwable",
      "varArgs" : false,
      "annotations" : [ ]
    } ],
    "thrownTypes" : [ ],
    "varArgs" : false,
    "documentation" : " Forces the given throwable to be thrown.\n"
  }, {
    "name" : "getBytes",
    "qualifiedName" : "io.fluxzero.common.ObjectUtils#getBytes",
    "returnType" : "byte[]",
    "modifiers" : [ "public", "static" ],
    "annotations" : [ ],
    "typeParameters" : [ ],
    "parameters" : [ {
      "name" : "buffer",
      "type" : "java.nio.ByteBuffer",
      "varArgs" : false,
      "annotations" : [ ]
    } ],
    "thrownTypes" : [ ],
    "varArgs" : false,
    "documentation" : " Extracts the byte array from a {@link ByteBuffer}.\n"
  }, {
    "name" : "ifTrue",
    "qualifiedName" : "io.fluxzero.common.ObjectUtils#ifTrue",
    "returnType" : "java.util.function.Consumer<java.lang.Runnable>",
    "modifiers" : [ "public", "static" ],
    "annotations" : [ ],
    "typeParameters" : [ ],
    "parameters" : [ {
      "name" : "check",
      "type" : "boolean",
      "varArgs" : false,
      "annotations" : [ ]
    } ],
    "thrownTypes" : [ ],
    "varArgs" : false,
    "documentation" : " Returns a consumer that runs the task only if {@code check} is true.\n"
  }, {
    "name" : "iterate",
    "qualifiedName" : "io.fluxzero.common.ObjectUtils#iterate",
    "returnType" : "java.util.stream.Stream<T>",
    "modifiers" : [ "public", "static" ],
    "annotations" : [ ],
    "typeParameters" : [ "T" ],
    "parameters" : [ {
      "name" : "seed",
      "type" : "T",
      "varArgs" : false,
      "annotations" : [ ]
    }, {
      "name" : "f",
      "type" : "java.util.function.UnaryOperator<T>",
      "varArgs" : false,
      "annotations" : [ ]
    }, {
      "name" : "breakCondition",
      "type" : "java.util.function.Predicate<T>",
      "varArgs" : false,
      "annotations" : [ ]
    } ],
    "thrownTypes" : [ ],
    "varArgs" : false,
    "documentation" : " Creates a stream that stops once the break condition evaluates true.\n"
  }, {
    "name" : "join",
    "qualifiedName" : "io.fluxzero.common.ObjectUtils#join",
    "returnType" : "byte[]",
    "modifiers" : [ "public", "static" ],
    "annotations" : [ {
      "annotationType" : "lombok.SneakyThrows",
      "values" : {}
    } ],
    "typeParameters" : [ ],
    "parameters" : [ {
      "name" : "chunks",
      "type" : "byte[][]",
      "varArgs" : true,
      "annotations" : [ ]
    } ],
    "thrownTypes" : [ ],
    "varArgs" : true,
    "documentation" : " Combines multiple byte arrays into a single byte array by concatenating their contents in the given order.\n"
  }, {
    "name" : "memoize",
    "qualifiedName" : "io.fluxzero.common.ObjectUtils#memoize",
    "returnType" : "io.fluxzero.common.MemoizingBiFunction<T,U,R>",
    "modifiers" : [ "public", "static" ],
    "annotations" : [ ],
    "typeParameters" : [ "T", "U", "R" ],
    "parameters" : [ {
      "name" : "supplier",
      "type" : "java.util.function.BiFunction<T,U,R>",
      "varArgs" : false,
      "annotations" : [ ]
    } ],
    "thrownTypes" : [ ],
    "varArgs" : false,
    "documentation" : null
  }, {
    "name" : "memoize",
    "qualifiedName" : "io.fluxzero.common.ObjectUtils#memoize",
    "returnType" : "io.fluxzero.common.MemoizingFunction<K,V>",
    "modifiers" : [ "public", "static" ],
    "annotations" : [ ],
    "typeParameters" : [ "K", "V" ],
    "parameters" : [ {
      "name" : "supplier",
      "type" : "java.util.function.Function<K,V>",
      "varArgs" : false,
      "annotations" : [ ]
    } ],
    "thrownTypes" : [ ],
    "varArgs" : false,
    "documentation" : null
  }, {
    "name" : "memoize",
    "qualifiedName" : "io.fluxzero.common.ObjectUtils#memoize",
    "returnType" : "io.fluxzero.common.MemoizingSupplier<T>",
    "modifiers" : [ "public", "static" ],
    "annotations" : [ ],
    "typeParameters" : [ "T" ],
    "parameters" : [ {
      "name" : "supplier",
      "type" : "java.util.function.Supplier<T>",
      "varArgs" : false,
      "annotations" : [ ]
    } ],
    "thrownTypes" : [ ],
    "varArgs" : false,
    "documentation" : null
  }, {
    "name" : "merge",
    "qualifiedName" : "io.fluxzero.common.ObjectUtils#merge",
    "returnType" : "java.util.Properties",
    "modifiers" : [ "public", "static" ],
    "annotations" : [ ],
    "typeParameters" : [ ],
    "parameters" : [ {
      "name" : "a",
      "type" : "java.util.Properties",
      "varArgs" : false,
      "annotations" : [ ]
    }, {
      "name" : "b",
      "type" : "java.util.Properties",
      "varArgs" : false,
      "annotations" : [ ]
    } ],
    "thrownTypes" : [ ],
    "varArgs" : false,
    "documentation" : " Merges two Properties instances into a new one.\n"
  }, {
    "name" : "newPlatformThreadFactory",
    "qualifiedName" : "io.fluxzero.common.ObjectUtils#newPlatformThreadFactory",
    "returnType" : "java.util.concurrent.ThreadFactory",
    "modifiers" : [ "public", "static" ],
    "annotations" : [ ],
    "typeParameters" : [ ],
    "parameters" : [ {
      "name" : "prefix",
      "type" : "java.lang.String",
      "varArgs" : false,
      "annotations" : [ ]
    } ],
    "thrownTypes" : [ ],
    "varArgs" : false,
    "documentation" : " Creates a new {@link ThreadFactory} with a named prefix.\n"
  }, {
    "name" : "newVirtualThreadFactory",
    "qualifiedName" : "io.fluxzero.common.ObjectUtils#newVirtualThreadFactory",
    "returnType" : "java.util.concurrent.ThreadFactory",
    "modifiers" : [ "public", "static" ],
    "annotations" : [ ],
    "typeParameters" : [ ],
    "parameters" : [ {
      "name" : "prefix",
      "type" : "java.lang.String",
      "varArgs" : false,
      "annotations" : [ ]
    } ],
    "thrownTypes" : [ ],
    "varArgs" : false,
    "documentation" : " Creates a new {@link ThreadFactory} with a named prefix.\n"
  }, {
    "name" : "noOpBiPredicate",
    "qualifiedName" : "io.fluxzero.common.ObjectUtils#noOpBiPredicate",
    "returnType" : "java.util.function.BiPredicate<T,U>",
    "modifiers" : [ "public", "static" ],
    "annotations" : [ {
      "annotationType" : "java.lang.SuppressWarnings",
      "values" : {
        "value" : "\"unchecked\""
      }
    } ],
    "typeParameters" : [ "T", "U" ],
    "parameters" : [ ],
    "thrownTypes" : [ ],
    "varArgs" : false,
    "documentation" : " Returns a bi-predicate that always evaluates to true.\n"
  }, {
    "name" : "noOpPredicate",
    "qualifiedName" : "io.fluxzero.common.ObjectUtils#noOpPredicate",
    "returnType" : "java.util.function.Predicate<T>",
    "modifiers" : [ "public", "static" ],
    "annotations" : [ {
      "annotationType" : "java.lang.SuppressWarnings",
      "values" : {
        "value" : "\"unchecked\""
      }
    } ],
    "typeParameters" : [ "T" ],
    "parameters" : [ ],
    "thrownTypes" : [ ],
    "varArgs" : false,
    "documentation" : " Returns a predicate that always evaluates to true.\n"
  }, {
    "name" : "run",
    "qualifiedName" : "io.fluxzero.common.ObjectUtils#run",
    "returnType" : "void",
    "modifiers" : [ "public", "static" ],
    "annotations" : [ {
      "annotationType" : "lombok.SneakyThrows",
      "values" : {}
    } ],
    "typeParameters" : [ ],
    "parameters" : [ {
      "name" : "runnable",
      "type" : "io.fluxzero.common.ThrowingRunnable",
      "varArgs" : false,
      "annotations" : [ ]
    } ],
    "thrownTypes" : [ ],
    "varArgs" : false,
    "documentation" : " Executes the runnable, forcibly rethrowing exceptions as unchecked.\n"
  }, {
    "name" : "silentTest",
    "qualifiedName" : "io.fluxzero.common.ObjectUtils#silentTest",
    "returnType" : "java.util.function.Predicate<T>",
    "modifiers" : [ "public", "static" ],
    "annotations" : [ ],
    "typeParameters" : [ "T" ],
    "parameters" : [ {
      "name" : "predicate",
      "type" : "java.util.function.Predicate<T>",
      "varArgs" : false,
      "annotations" : [ ]
    } ],
    "thrownTypes" : [ ],
    "varArgs" : false,
    "documentation" : " Returns a predicate that silently returns false when the given predicate throws an error.\n"
  }, {
    "name" : "tryAccept",
    "qualifiedName" : "io.fluxzero.common.ObjectUtils#tryAccept",
    "returnType" : "java.util.function.Consumer<? super T>",
    "modifiers" : [ "public", "static" ],
    "annotations" : [ ],
    "typeParameters" : [ "T" ],
    "parameters" : [ {
      "name" : "consumer",
      "type" : "java.util.function.Consumer<? super T>",
      "varArgs" : false,
      "annotations" : [ ]
    } ],
    "thrownTypes" : [ ],
    "varArgs" : false,
    "documentation" : " Returns a consumer that logs errors instead of propagating them.\n"
  }, {
    "name" : "tryCatch",
    "qualifiedName" : "io.fluxzero.common.ObjectUtils#tryCatch",
    "returnType" : "java.lang.Runnable",
    "modifiers" : [ "public", "static" ],
    "annotations" : [ ],
    "typeParameters" : [ ],
    "parameters" : [ {
      "name" : "runnable",
      "type" : "java.lang.Runnable",
      "varArgs" : false,
      "annotations" : [ ]
    } ],
    "thrownTypes" : [ ],
    "varArgs" : false,
    "documentation" : " Wraps a runnable in a try/catch block that logs any exception on execution.\n"
  }, {
    "name" : "tryRun",
    "qualifiedName" : "io.fluxzero.common.ObjectUtils#tryRun",
    "returnType" : "void",
    "modifiers" : [ "public", "static" ],
    "annotations" : [ ],
    "typeParameters" : [ ],
    "parameters" : [ {
      "name" : "task",
      "type" : "java.lang.Runnable",
      "varArgs" : false,
      "annotations" : [ ]
    } ],
    "thrownTypes" : [ ],
    "varArgs" : false,
    "documentation" : " Executes the runnable and logs any thrown exception.\n"
  }, {
    "name" : "unwrapException",
    "qualifiedName" : "io.fluxzero.common.ObjectUtils#unwrapException",
    "returnType" : "java.lang.Throwable",
    "modifiers" : [ "public", "static" ],
    "annotations" : [ ],
    "typeParameters" : [ ],
    "parameters" : [ {
      "name" : "e",
      "type" : "java.lang.Throwable",
      "varArgs" : false,
      "annotations" : [ ]
    } ],
    "thrownTypes" : [ ],
    "varArgs" : false,
    "documentation" : " Recursively unwraps the cause of common wrapping exceptions.\n"
  } ],
  "enumConstants" : [ ],
  "recordComponents" : [ ],
  "nestedTypes" : [ {
    "name" : "BreakingSpliterator",
    "qualifiedName" : "io.fluxzero.common.ObjectUtils$BreakingSpliterator",
    "kind" : "class",
    "modifiers" : [ "private", "static" ],
    "annotations" : [ ]
  }, {
    "name" : "PrefixedThreadFactory",
    "qualifiedName" : "io.fluxzero.common.ObjectUtils$PrefixedThreadFactory",
    "kind" : "class",
    "modifiers" : [ "private", "static" ],
    "annotations" : [ ]
  } ]
}
