{
  "name" : "DescendantTargetMetadata",
  "qualifiedName" : "io.fluxzero.sdk.modeling.ImmutableEntity$DescendantTargetMetadata",
  "packageName" : "io.fluxzero.sdk.modeling",
  "kind" : "record",
  "modifiers" : [ "final", "private", "static" ],
  "annotations" : [ ],
  "documentation" : null,
  "typeParameters" : [ ],
  "superClass" : "java.lang.Record",
  "interfaces" : [ ],
  "fields" : [ {
    "name" : "CERTAIN_EMPTY",
    "qualifiedName" : "io.fluxzero.sdk.modeling.ImmutableEntity$DescendantTargetMetadata.CERTAIN_EMPTY",
    "type" : "io.fluxzero.sdk.modeling.ImmutableEntity.DescendantTargetMetadata",
    "modifiers" : [ "final", "private", "static" ],
    "annotations" : [ ],
    "documentation" : null,
    "constantValue" : null
  }, {
    "name" : "certain",
    "qualifiedName" : "io.fluxzero.sdk.modeling.ImmutableEntity$DescendantTargetMetadata.certain",
    "type" : "boolean",
    "modifiers" : [ "final", "private" ],
    "annotations" : [ ],
    "documentation" : null,
    "constantValue" : null
  }, {
    "name" : "idProperties",
    "qualifiedName" : "io.fluxzero.sdk.modeling.ImmutableEntity$DescendantTargetMetadata.idProperties",
    "type" : "java.util.Set<java.lang.String>",
    "modifiers" : [ "final", "private" ],
    "annotations" : [ ],
    "documentation" : null,
    "constantValue" : null
  } ],
  "constructors" : [ {
    "name" : "DescendantTargetMetadata",
    "qualifiedName" : "io.fluxzero.sdk.modeling.ImmutableEntity$DescendantTargetMetadata#DescendantTargetMetadata",
    "modifiers" : [ "private" ],
    "annotations" : [ ],
    "typeParameters" : [ ],
    "parameters" : [ {
      "name" : "idProperties",
      "type" : "java.util.Set<java.lang.String>",
      "varArgs" : false,
      "annotations" : [ ]
    }, {
      "name" : "certain",
      "type" : "boolean",
      "varArgs" : false,
      "annotations" : [ ]
    } ],
    "thrownTypes" : [ ],
    "varArgs" : false,
    "documentation" : null
  } ],
  "methods" : [ {
    "name" : "certain",
    "qualifiedName" : "io.fluxzero.sdk.modeling.ImmutableEntity$DescendantTargetMetadata#certain",
    "returnType" : "boolean",
    "modifiers" : [ "public" ],
    "annotations" : [ ],
    "typeParameters" : [ ],
    "parameters" : [ ],
    "thrownTypes" : [ ],
    "varArgs" : false,
    "documentation" : null
  }, {
    "name" : "equals",
    "qualifiedName" : "io.fluxzero.sdk.modeling.ImmutableEntity$DescendantTargetMetadata#equals",
    "returnType" : "boolean",
    "modifiers" : [ "final", "public" ],
    "annotations" : [ ],
    "typeParameters" : [ ],
    "parameters" : [ {
      "name" : "o",
      "type" : "java.lang.Object",
      "varArgs" : false,
      "annotations" : [ ]
    } ],
    "thrownTypes" : [ ],
    "varArgs" : false,
    "documentation" : null
  }, {
    "name" : "hashCode",
    "qualifiedName" : "io.fluxzero.sdk.modeling.ImmutableEntity$DescendantTargetMetadata#hashCode",
    "returnType" : "int",
    "modifiers" : [ "final", "public" ],
    "annotations" : [ ],
    "typeParameters" : [ ],
    "parameters" : [ ],
    "thrownTypes" : [ ],
    "varArgs" : false,
    "documentation" : null
  }, {
    "name" : "idProperties",
    "qualifiedName" : "io.fluxzero.sdk.modeling.ImmutableEntity$DescendantTargetMetadata#idProperties",
    "returnType" : "java.util.Set<java.lang.String>",
    "modifiers" : [ "public" ],
    "annotations" : [ ],
    "typeParameters" : [ ],
    "parameters" : [ ],
    "thrownTypes" : [ ],
    "varArgs" : false,
    "documentation" : null
  }, {
    "name" : "toString",
    "qualifiedName" : "io.fluxzero.sdk.modeling.ImmutableEntity$DescendantTargetMetadata#toString",
    "returnType" : "java.lang.String",
    "modifiers" : [ "final", "public" ],
    "annotations" : [ ],
    "typeParameters" : [ ],
    "parameters" : [ ],
    "thrownTypes" : [ ],
    "varArgs" : false,
    "documentation" : null
  } ],
  "enumConstants" : [ ],
  "recordComponents" : [ {
    "name" : "certain",
    "type" : "boolean",
    "annotations" : [ ],
    "documentation" : null
  }, {
    "name" : "idProperties",
    "type" : "java.util.Set<java.lang.String>",
    "annotations" : [ ],
    "documentation" : null
  } ],
  "nestedTypes" : [ ]
}
