{
  "name" : "HandleMetrics",
  "qualifiedName" : "io.fluxzero.sdk.tracking.handling.HandleMetrics",
  "packageName" : "io.fluxzero.sdk.tracking.handling",
  "kind" : "annotation_type",
  "modifiers" : [ "abstract", "public" ],
  "annotations" : [ {
    "annotationType" : "java.lang.annotation.Documented",
    "values" : {}
  }, {
    "annotationType" : "java.lang.annotation.Retention",
    "values" : {
      "value" : "RUNTIME"
    }
  }, {
    "annotationType" : "java.lang.annotation.Target",
    "values" : {
      "value" : "METHOD,CONSTRUCTOR"
    }
  }, {
    "annotationType" : "io.fluxzero.sdk.tracking.handling.HandleMessage",
    "values" : {
      "value" : "METRICS"
    }
  } ],
  "documentation" : " Marks a method or constructor as a handler for internal metrics events ({@link MessageType#METRICS}).\n <p>\n Metrics messages are emitted by Fluxzero applications and the Fluxzero Runtime to report on internal operations such\n as read throughput, search activity, store position updates, or handler performance. These messages are valuable for\n observability, debugging, auditing, and building custom monitoring or alerting systems.\n </p>\n\n <p>\n This annotation allows applications to process metrics events, optionally filtered by payload type. It is a concrete\n specialization of {@link HandleMessage} for {@link MessageType#METRICS}.\n </p>\n\n <h2>Use Cases</h2>\n <ul>\n   <li>Monitoring how frequently specific projections are accessed</li>\n   <li>Tracking search volume or performance for the document store</li>\n   <li>Building dashboards with application-specific system insights</li>\n   <li>Capturing store/read latency or error patterns</li>\n </ul>\n\n @see HandleMessage\n @see MessageType#METRICS\n",
  "typeParameters" : [ ],
  "superClass" : null,
  "interfaces" : [ "java.lang.annotation.Annotation" ],
  "fields" : [ ],
  "constructors" : [ ],
  "methods" : [ {
    "name" : "allowedClasses",
    "qualifiedName" : "io.fluxzero.sdk.tracking.handling.HandleMetrics#allowedClasses",
    "returnType" : "java.lang.Class<?>[]",
    "modifiers" : [ "abstract", "public" ],
    "annotations" : [ ],
    "typeParameters" : [ ],
    "parameters" : [ ],
    "thrownTypes" : [ ],
    "varArgs" : false,
    "documentation" : " Restricts which payload types this handler may be invoked for.\n"
  }, {
    "name" : "disabled",
    "qualifiedName" : "io.fluxzero.sdk.tracking.handling.HandleMetrics#disabled",
    "returnType" : "boolean",
    "modifiers" : [ "abstract", "public" ],
    "annotations" : [ ],
    "typeParameters" : [ ],
    "parameters" : [ ],
    "thrownTypes" : [ ],
    "varArgs" : false,
    "documentation" : " If {@code true}, disables this handler during discovery.\n"
  } ],
  "enumConstants" : [ ],
  "recordComponents" : [ ],
  "nestedTypes" : [ ]
}
