{
  "name" : "ResultBatch",
  "qualifiedName" : "io.fluxzero.common.api.ResultBatch",
  "packageName" : "io.fluxzero.common.api",
  "kind" : "class",
  "modifiers" : [ "public" ],
  "annotations" : [ {
    "annotationType" : "lombok.Value",
    "values" : {}
  } ],
  "documentation" : " Represents a batch of results returned from the Fluxzero Runtime in response to a {@link RequestBatch}.\n <p>\n Each {@link RequestResult} in this list corresponds to one of the requests in the original batch and is\n matched using {@code requestId}. Note that result order is not guaranteed to match the order of the requests.\n </p>\n\n <h2>Result Matching</h2>\n The Fluxzero Java SDK automatically routes each {@link RequestResult} back to its originating {@link Request}\n using the unique {@code requestId}.\n\n <h2>Error Handling</h2>\n If any request fails, its result will be an {@link ErrorResult}. The client will complete the\n corresponding {@code CompletableFuture} exceptionally using a {@code ServiceException}.\n\n @see RequestBatch\n @see RequestResult\n @see ErrorResult\n",
  "typeParameters" : [ ],
  "superClass" : "java.lang.Object",
  "interfaces" : [ "io.fluxzero.common.api.JsonType" ],
  "fields" : [ {
    "name" : "results",
    "qualifiedName" : "io.fluxzero.common.api.ResultBatch.results",
    "type" : "java.util.List<io.fluxzero.common.api.RequestResult>",
    "modifiers" : [ ],
    "annotations" : [ ],
    "documentation" : " The list of results corresponding to previously sent requests.\n <p>\n Result order is not guaranteed to match the original request order.\n Use {@link RequestResult#getRequestId()} to match responses.\n",
    "constantValue" : null
  } ],
  "constructors" : [ {
    "name" : "ResultBatch",
    "qualifiedName" : "io.fluxzero.common.api.ResultBatch#ResultBatch",
    "modifiers" : [ "public" ],
    "annotations" : [ ],
    "typeParameters" : [ ],
    "parameters" : [ ],
    "thrownTypes" : [ ],
    "varArgs" : false,
    "documentation" : null
  } ],
  "methods" : [ ],
  "enumConstants" : [ ],
  "recordComponents" : [ ],
  "nestedTypes" : [ ]
}
